coherent/deps/__init__.py
coherent/deps/__main__.py
coherent/deps/imports.py
coherent/deps/pypi.py
coherent/deps/distributions/load.py
coherent/deps/distributions/process.py
coherent_deps-1.6.0.dist-info/entry_points.txt
coherent_deps-1.6.0.dist-info/licenses/LICENSE
coherent_deps-1.6.0.dist-info/WHEEL
coherent_deps-1.6.0.dist-info/METADATA
coherent_deps-1.6.0.dist-info/RECORD
