Metadata-Version: 2.4
Name: coherent.deps
Version: 1.6.0
Summary: Utilities for resolving imports to dependencies.
Author-email: "Jason R. Coombs" <jaraco@jaraco.com>
Requires-Python: >= 3.9
License-Expression: MIT
Classifier: Development Status :: 5 - Production/Stable
Classifier: Intended Audience :: Developers
Classifier: Programming Language :: Python :: 3
Classifier: Programming Language :: Python :: 3 :: Only
License-File: LICENSE
Requires-Dist: jaraco.ui
Requires-Dist: more-itertools
Requires-Dist: tqdm
Requires-Dist: typer
Requires-Dist: jaraco.context
Requires-Dist: jaraco.collections
Requires-Dist: jaraco.mongodb
Requires-Dist: keyring
Requires-Dist: tempora
Requires-Dist: jaraco.compat
Requires-Dist: jaraco.functools
Requires-Dist: requests
Requires-Dist: requests-file
Requires-Dist: requests-toolbelt
Requires-Dist: retry-requests
Requires-Dist: zipp
Project-URL: Source, https://github.com/coherent-oss/coherent.deps
